fastapi_alchemy/__init__.py
fastapi_alchemy/context.py
fastapi_alchemy/exceptions.py
fastapi_alchemy/initializer.py
fastapi_alchemy/middleware.py
fastapi_alchemy-0.1.0.dist-info/WHEEL
fastapi_alchemy-0.1.0.dist-info/METADATA
fastapi_alchemy-0.1.0.dist-info/RECORD
