Metadata-Version: 2.1
Name: fastapi-alchemy
Version: 0.1.0
Summary: 
Author: teamhide
Author-email: padocon@naver.com
Requires-Python: >=3.8,<4.0
Classifier: Programming Language :: Python :: 3
Classifier: Programming Language :: Python :: 3.10
Classifier: Programming Language :: Python :: 3.8
Classifier: Programming Language :: Python :: 3.9
Requires-Dist: SQLAlchemy[asyncio] (>=1.4.40,<2.0.0)
